huechanger/__init__.py
huechanger-0.1.dist-info/DESCRIPTION.rst
huechanger-0.1.dist-info/METADATA
huechanger-0.1.dist-info/RECORD
huechanger-0.1.dist-info/WHEEL
huechanger-0.1.dist-info/metadata.json
huechanger-0.1.dist-info/top_level.txt
