Metadata-Version: 2.0
Name: huechanger
Version: 0.1
Summary: Change color of images
Home-page: https://github.com/guemues/hue-changer
Author: Orcun Gumus
Author-email: orcungumus@gmail.com
License: UNKNOWN
Download-URL: https://github.com/guemues/hue-changer/archive/0.1.tar.gz
Keywords: color
Platform: UNKNOWN
Requires-Dist: certifi (==2017.11.5)
Requires-Dist: chardet (==3.0.4)
Requires-Dist: cycler (==0.10.0)
Requires-Dist: idna (==2.6)
Requires-Dist: matplotlib (==2.1.0)
Requires-Dist: nose (==1.3.7)
Requires-Dist: numpy (==1.13.3)
Requires-Dist: opencv-python (==3.3.0.10)
Requires-Dist: pyparsing (==2.2.0)
Requires-Dist: python-dateutil (==2.6.1)
Requires-Dist: pytz (==2017.3)
Requires-Dist: requests (==2.18.4)
Requires-Dist: six (==1.11.0)
Requires-Dist: urllib3 (==1.22)
